{
  "tout_departement": {
    "disponibles": 471,
    "total": 2611,
    "creneaux": 57224
  },
  "01": {
    "disponibles": 9,
    "total": 15,
    "creneaux": 724
  },
  "02": {
    "disponibles": 0,
    "total": 28,
    "creneaux": 0
  },
  "03": {
    "disponibles": 1,
    "total": 10,
    "creneaux": 6
  },
  "04": {
    "disponibles": 4,
    "total": 13,
    "creneaux": 156
  },
  "05": {
    "disponibles": 4,
    "total": 9,
    "creneaux": 225
  },
  "06": {
    "disponibles": 11,
    "total": 48,
    "creneaux": 482
  },
  "07": {
    "disponibles": 3,
    "total": 14,
    "creneaux": 491
  },
  "08": {
    "disponibles": 1,
    "total": 24,
    "creneaux": 1
  },
  "09": {
    "disponibles": 1,
    "total": 15,
    "creneaux": 39
  },
  "10": {
    "disponibles": 1,
    "total": 13,
    "creneaux": 48
  },
  "11": {
    "disponibles": 2,
    "total": 16,
    "creneaux": 795
  },
  "12": {
    "disponibles": 2,
    "total": 8,
    "creneaux": 102
  },
  "13": {
    "disponibles": 16,
    "total": 70,
    "creneaux": 1474
  },
  "14": {
    "disponibles": 5,
    "total": 26,
    "creneaux": 450
  },
  "15": {
    "disponibles": 0,
    "total": 6,
    "creneaux": 0
  },
  "16": {
    "disponibles": 2,
    "total": 19,
    "creneaux": 242
  },
  "17": {
    "disponibles": 0,
    "total": 32,
    "creneaux": 0
  },
  "18": {
    "disponibles": 4,
    "total": 39,
    "creneaux": 120
  },
  "19": {
    "disponibles": 1,
    "total": 22,
    "creneaux": 4
  },
  "21": {
    "disponibles": 0,
    "total": 32,
    "creneaux": 0
  },
  "22": {
    "disponibles": 4,
    "total": 18,
    "creneaux": 1316
  },
  "23": {
    "disponibles": 0,
    "total": 9,
    "creneaux": 0
  },
  "24": {
    "disponibles": 2,
    "total": 29,
    "creneaux": 177
  },
  "25": {
    "disponibles": 0,
    "total": 20,
    "creneaux": 0
  },
  "26": {
    "disponibles": 4,
    "total": 17,
    "creneaux": 649
  },
  "27": {
    "disponibles": 5,
    "total": 23,
    "creneaux": 263
  },
  "28": {
    "disponibles": 2,
    "total": 25,
    "creneaux": 53
  },
  "29": {
    "disponibles": 1,
    "total": 29,
    "creneaux": 5
  },
  "2A": {
    "disponibles": 1,
    "total": 10,
    "creneaux": 134
  },
  "2B": {
    "disponibles": 3,
    "total": 12,
    "creneaux": 378
  },
  "30": {
    "disponibles": 9,
    "total": 29,
    "creneaux": 1298
  },
  "31": {
    "disponibles": 16,
    "total": 46,
    "creneaux": 2732
  },
  "32": {
    "disponibles": 1,
    "total": 21,
    "creneaux": 82
  },
  "33": {
    "disponibles": 14,
    "total": 46,
    "creneaux": 1548
  },
  "34": {
    "disponibles": 0,
    "total": 43,
    "creneaux": 0
  },
  "35": {
    "disponibles": 7,
    "total": 27,
    "creneaux": 727
  },
  "36": {
    "disponibles": 1,
    "total": 18,
    "creneaux": 71
  },
  "37": {
    "disponibles": 2,
    "total": 16,
    "creneaux": 256
  },
  "38": {
    "disponibles": 11,
    "total": 26,
    "creneaux": 5562
  },
  "39": {
    "disponibles": 4,
    "total": 23,
    "creneaux": 90
  },
  "40": {
    "disponibles": 2,
    "total": 23,
    "creneaux": 17
  },
  "41": {
    "disponibles": 1,
    "total": 36,
    "creneaux": 91
  },
  "42": {
    "disponibles": 9,
    "total": 26,
    "creneaux": 1539
  },
  "43": {
    "disponibles": 0,
    "total": 6,
    "creneaux": 0
  },
  "44": {
    "disponibles": 4,
    "total": 28,
    "creneaux": 337
  },
  "45": {
    "disponibles": 2,
    "total": 19,
    "creneaux": 191
  },
  "46": {
    "disponibles": 8,
    "total": 23,
    "creneaux": 940
  },
  "47": {
    "disponibles": 2,
    "total": 9,
    "creneaux": 719
  },
  "48": {
    "disponibles": 0,
    "total": 9,
    "creneaux": 0
  },
  "49": {
    "disponibles": 4,
    "total": 12,
    "creneaux": 488
  },
  "50": {
    "disponibles": 4,
    "total": 17,
    "creneaux": 3184
  },
  "51": {
    "disponibles": 1,
    "total": 25,
    "creneaux": 28
  },
  "52": {
    "disponibles": 0,
    "total": 5,
    "creneaux": 0
  },
  "53": {
    "disponibles": 3,
    "total": 13,
    "creneaux": 78
  },
  "54": {
    "disponibles": 3,
    "total": 32,
    "creneaux": 135
  },
  "55": {
    "disponibles": 5,
    "total": 23,
    "creneaux": 176
  },
  "56": {
    "disponibles": 5,
    "total": 21,
    "creneaux": 1238
  },
  "57": {
    "disponibles": 2,
    "total": 33,
    "creneaux": 120
  },
  "58": {
    "disponibles": 4,
    "total": 15,
    "creneaux": 249
  },
  "59": {
    "disponibles": 32,
    "total": 109,
    "creneaux": 623
  },
  "60": {
    "disponibles": 3,
    "total": 31,
    "creneaux": 27
  },
  "61": {
    "disponibles": 6,
    "total": 13,
    "creneaux": 489
  },
  "62": {
    "disponibles": 11,
    "total": 61,
    "creneaux": 878
  },
  "63": {
    "disponibles": 4,
    "total": 20,
    "creneaux": 54
  },
  "64": {
    "disponibles": 11,
    "total": 34,
    "creneaux": 1003
  },
  "65": {
    "disponibles": 1,
    "total": 8,
    "creneaux": 13
  },
  "66": {
    "disponibles": 2,
    "total": 14,
    "creneaux": 360
  },
  "67": {
    "disponibles": 10,
    "total": 39,
    "creneaux": 340
  },
  "68": {
    "disponibles": 8,
    "total": 23,
    "creneaux": 269
  },
  "69": {
    "disponibles": 4,
    "total": 51,
    "creneaux": 50
  },
  "70": {
    "disponibles": 1,
    "total": 11,
    "creneaux": 6
  },
  "71": {
    "disponibles": 16,
    "total": 28,
    "creneaux": 2100
  },
  "72": {
    "disponibles": 0,
    "total": 19,
    "creneaux": 0
  },
  "73": {
    "disponibles": 10,
    "total": 25,
    "creneaux": 1362
  },
  "74": {
    "disponibles": 16,
    "total": 31,
    "creneaux": 1599
  },
  "75": {
    "disponibles": 18,
    "total": 105,
    "creneaux": 1067
  },
  "76": {
    "disponibles": 11,
    "total": 36,
    "creneaux": 802
  },
  "77": {
    "disponibles": 1,
    "total": 41,
    "creneaux": 1
  },
  "78": {
    "disponibles": 4,
    "total": 39,
    "creneaux": 367
  },
  "79": {
    "disponibles": 1,
    "total": 27,
    "creneaux": 21
  },
  "80": {
    "disponibles": 6,
    "total": 24,
    "creneaux": 137
  },
  "81": {
    "disponibles": 5,
    "total": 16,
    "creneaux": 861
  },
  "82": {
    "disponibles": 3,
    "total": 11,
    "creneaux": 548
  },
  "83": {
    "disponibles": 6,
    "total": 46,
    "creneaux": 1270
  },
  "84": {
    "disponibles": 1,
    "total": 24,
    "creneaux": 138
  },
  "85": {
    "disponibles": 2,
    "total": 14,
    "creneaux": 254
  },
  "86": {
    "disponibles": 0,
    "total": 22,
    "creneaux": 0
  },
  "87": {
    "disponibles": 0,
    "total": 14,
    "creneaux": 0
  },
  "88": {
    "disponibles": 1,
    "total": 11,
    "creneaux": 216
  },
  "89": {
    "disponibles": 1,
    "total": 22,
    "creneaux": 38
  },
  "90": {
    "disponibles": 4,
    "total": 6,
    "creneaux": 590
  },
  "91": {
    "disponibles": 3,
    "total": 47,
    "creneaux": 238
  },
  "92": {
    "disponibles": 15,
    "total": 77,
    "creneaux": 141
  },
  "93": {
    "disponibles": 6,
    "total": 56,
    "creneaux": 479
  },
  "94": {
    "disponibles": 7,
    "total": 39,
    "creneaux": 166
  },
  "95": {
    "disponibles": 5,
    "total": 48,
    "creneaux": 329
  },
  "971": {
    "disponibles": 7,
    "total": 14,
    "creneaux": 372
  },
  "972": {
    "disponibles": 4,
    "total": 8,
    "creneaux": 3442
  },
  "973": {
    "disponibles": 3,
    "total": 4,
    "creneaux": 143
  },
  "974": {
    "disponibles": 9,
    "total": 19,
    "creneaux": 6201
  },
  "976": {
    "disponibles": 0,
    "total": 3,
    "creneaux": 0
  }
}